cbe/__init__.py
cbe/open_data.py
cbe/portal.py
cbe/schema.sql
cbe-0.1.8.dist-info/licenses/LICENSE
cbe-0.1.8.dist-info/METADATA
cbe-0.1.8.dist-info/WHEEL
cbe-0.1.8.dist-info/top_level.txt
cbe-0.1.8.dist-info/RECORD
