Metadata-Version: 2.4
Name: cbe
Version: 0.1.8
Summary: Python package for interacting with the Crossroads Bank for Enterprises (CBE, BCE, KBO, ZDU)
Home-page: https://github.com/azizo-b/CBE
Author: Aziz Baatout
License: MIT
Keywords: cbe,kbo,bce,belgium,open data,public search
License-File: LICENSE
Requires-Dist: requests
Requires-Dist: pandas
Requires-Dist: beautifulsoup4
Dynamic: author
Dynamic: description
Dynamic: description-content-type
Dynamic: home-page
Dynamic: keywords
Dynamic: license
Dynamic: license-file
Dynamic: requires-dist
Dynamic: summary
